<?xml version="1.0" encoding="utf-8"?>
<GlobalVariables>
  <Variable id="JSESSIONID" usecookie="true"/>
  <Variable id="gv_webRoot" initval="http://localhost:8080/"/>
  <Variable id="gv_httpObj"/>
  <Variable id="gv_temp"/>
  <Variable id="gv_ipAddr"/>
  <Variable id="gv_menuId"/>
  <Variable id="gv_progrmId"/>
  <Variable id="gv_helpId"/>
  <Variable id="gv_runMode" initval="L"/>
  <Variable id="gv_mdi" initval="N"/>
  <Variable id="gv_chartPath" initval="http://localhost:8080/fusionchart/"/>
  <Variable id="gv_ozReport" initval="http://localhost:8080/sc/cmn/report/reportViewer.do"/>
  <Variable id="gv_ozReportProcessing" initval="http://localhost:8080/common/reportViewProcess.jsp"/>
  <Variable id="gv_helpView" initval="http://help.efoodist.com:8090/pages/viewpage.action?pageId="/>
  <Variable id="gv_noData" initval="URL('theme://images/grd_WF_NoDataImg.png')"/>
  <Variable id="gv_tranCancel" initval="Y"/>
  <Variable id="gv_sessionInit" initval="N"/>
  <Variable id="gv_ktagTokenField" initval="savedToken"/>
  <Variable id="gv_savedToken"/>
  <Variable id="outSavedToken"/>
  <Variable id="gv_xp_txdatatype" initval="0" usecookie="true"/>
  <Variable id="gv_blockMode" initval=""/>
  <Variable id="g_AuthLevel" initval="999"/>
  <Variable id="g_Cc_Cd" initval="AC008"/>
  <Variable id="g_Cc_Nm" initval="정보기획팀"/>
  <Variable id="g_CustCd" initval="227031"/>
  <Variable id="g_CustNm" initval="한양식품"/>
  <Variable id="g_Deptid" initval="300252"/>
  <Variable id="g_DeptNm" initval="본사 Staff 정보기획팀"/>
  <Variable id="g_EmpNo" initval="199710076"/>
  <Variable id="g_Main_Upjang"/>
  <Variable id="g_Main_UpjangNm"/>
  <Variable id="g_Mu_Cd" initval="2003"/>
  <Variable id="g_Mu_Nm" initval="외식사업부"/>
  <Variable id="g_Name" initval="개발자"/>
  <Variable id="g_OtCustCd"/>
  <Variable id="g_OtCustNm"/>
  <Variable id="g_Sc_Cd" initval="AT"/>
  <Variable id="g_Sc_Nm" initval="Staff"/>
  <Variable id="g_SystemId" initval="IFIS"/>
  <Variable id="g_AppId" initval="HWFS"/>
  <Variable id="g_Tm_Cd" initval="CEE"/>
  <Variable id="g_Tm_Nm" initval="외식영업팀"/>
  <Variable id="g_Upjang" initval="114352"/>
  <Variable id="g_UpjangGroup"/>
  <Variable id="g_UpjangNm" initval="FC외식 연세프라자점"/>
  <Variable id="g_UserGroup" initval="리조트"/>
  <Variable id="g_UserKind" initval="본부"/>
  <Variable id="g_Simple_Po_Yn" initval="N"/>
  <Variable id="g_Board_Mst" initval="관리자"/>
  <Dataset id="gds_userInfo">
    <ColumnInfo>
      <Column id="userid" type="string" size="32"/>
      <Column id="pswdChk" type="string" size="32"/>
      <Column id="usrNm" type="string" size="32"/>
      <Column id="usrEngNm" type="string" size="32"/>
      <Column id="rno" type="string" size="32"/>
      <Column id="offcCd" type="string" size="32"/>
      <Column id="offcNm" type="string" size="32"/>
      <Column id="ogCd" type="string" size="32"/>
      <Column id="ogNm" type="string" size="32"/>
      <Column id="posCd" type="string" size="32"/>
      <Column id="posNm" type="string" size="32"/>
      <Column id="psitNm" type="string" size="32"/>
      <Column id="pno" type="string" size="32"/>
      <Column id="faxNo" type="string" size="32"/>
      <Column id="mblPno" type="string" size="32"/>
      <Column id="zipNo" type="string" size="32"/>
      <Column id="addr" type="string" size="32"/>
      <Column id="emailAddr" type="string" size="32"/>
      <Column id="fnlConnIp" type="string" size="32"/>
      <Column id="fnlConnDtm" type="string" size="32"/>
      <Column id="bgnDt" type="string" size="32"/>
      <Column id="edt" type="string" size="32"/>
      <Column id="fnlModrId" type="string" size="32"/>
      <Column id="fnlModDtm" type="string" size="32"/>
      <Column id="certDn" type="string" size="32"/>
      <Column id="popupYn" type="string" size="32"/>
      <Column id="sesId" type="string" size="32"/>
      <Column id="pupMarkYn" type="string" size="32"/>
      <Column id="usrDivCd" type="string" size="32"/>
      <Column id="dfnYn" type="string" size="32"/>
      <Column id="smsUseYn" type="string" size="32"/>
      <Column id="persInfoAgreeYn" type="STRING" size="256"/>
      <Column id="persInfoMask" type="STRING" size="256"/>
      <Column id="persInfoProcLevel" type="STRING" size="256"/>
      <Column id="ctiUseYn" type="STRING" size="256"/>
      <Column id="ctiUserId" type="STRING" size="256"/>
      <Column id="authLevels" type="STRING" size="256"/>
      <Column id="introPage" type="STRING" size="256"/>
      <Column id="mainUpjangImg" type="STRING" size="256"/>
      <Column id="sysTypeCnt" type="STRING" size="256"/>
      <Column id="upjangCnt" type="STRING" size="256"/>
      <Column id="slipSabun" type="STRING" size="256"/>
    </ColumnInfo>
    <Rows>
      <Row>
        <Col id="userid">A000000</Col>
        <Col id="pswdChk">N</Col>
        <Col id="usrNm">홍길동</Col>
        <Col id="usrEngNm">Bak Kwang Chon</Col>
        <Col id="rno">5609291******</Col>
        <Col id="ogCd">1320113</Col>
        <Col id="ogNm">하나빌딩점</Col>
        <Col id="psitNm">총경</Col>
        <Col id="pno">02-3400-1131</Col>
        <Col id="faxNo">02-3400-1134</Col>
        <Col id="zipNo">138708</Col>
        <Col id="addr">서울 송파구 가락본동 경찰병원</Col>
        <Col id="emailAddr">bak1131@hanmail.net</Col>
        <Col id="fnlConnIp">10.14.22.29</Col>
        <Col id="fnlConnDtm">2006-11-24 08:54:28</Col>
        <Col id="bgnDt">20060306</Col>
        <Col id="edt">21001231</Col>
        <Col id="fnlModrId">BAK1131</Col>
        <Col id="fnlModDtm">2006-11-24 08:54:28</Col>
        <Col id="certDn">cn=백광천[037][010234],ou=nafis,o=NCASign,c=KR</Col>
        <Col id="popupYn">Y</Col>
        <Col id="pupMarkYn">N</Col>
        <Col id="dfnYn">N</Col>
        <Col id="offcNm">하나빌딩점</Col>
        <Col id="persInfoAgreeYn">Y</Col>
        <Col id="persInfoMask">YYYYYYYYYYYYYY</Col>
        <Col id="persInfoProcLevel">99</Col>
        <Col id="sysTypeCnt">2</Col>
        <Col id="upjangCnt">2</Col>
      </Row>
    </Rows>
  </Dataset>
  <Dataset id="gds_recentMenu">
    <ColumnInfo>
      <Column id="menuId" type="STRING" size="256"/>
      <Column id="menuName" type="STRING" size="256"/>
      <Column id="prgId" type="STRING" size="256"/>
      <Column id="helpId" type="STRING" size="256"/>
    </ColumnInfo>
    <Rows>
      <Row>
        <Col id="menuId">1719</Col>
        <Col id="menuName">메뉴관리</Col>
        <Col id="prgId">MenuMgmt</Col>
      </Row>
      <Row>
        <Col id="menuId">405</Col>
        <Col id="menuName">코드관리</Col>
        <Col id="prgId">MAC10010E.xfdl</Col>
      </Row>
      <Row>
        <Col id="menuId">408</Col>
        <Col id="menuName">인건비기준코드 등록</Col>
        <Col id="prgId">MAC10040E.xfdl</Col>
      </Row>
    </Rows>
  </Dataset>
  <Dataset id="gds_menu">
    <ColumnInfo>
      <Column id="sysId" type="STRING" size="256"/>
      <Column id="sysName" type="STRING" size="256"/>
      <Column id="menuId" type="STRING" size="256"/>
      <Column id="menuName" type="STRING" size="256"/>
      <Column id="parentMenuId" type="STRING" size="256"/>
      <Column id="prgId" type="STRING" size="256"/>
      <Column id="prgName" type="STRING" size="256"/>
      <Column id="prgPath" type="STRING" size="256"/>
      <Column id="menuType" type="STRING" size="256"/>
      <Column id="levels" type="STRING" size="256"/>
      <Column id="sortSeq" type="STRING" size="256"/>
      <Column id="useYn" type="STRING" size="256"/>
      <Column id="prgType" type="STRING" size="256"/>
      <Column id="leaderMenu" type="STRING" size="256"/>
      <Column id="isLeaf" type="INT" size="256"/>
      <Column id="callParam" type="STRING" size="256"/>
      <Column id="helpId" type="STRING" size="256"/>
    </ColumnInfo>
  </Dataset>
  <Dataset id="gds_mainMenu" onrowsetchanged="gds_mainMenu_onrowsetchanged"/>
  <Dataset id="gds_leftMenu" onrowsetchanged="gds_leftMenu_onrowsetchanged"/>
  <FilteredDataset id="gfds_menuSearch" binddataset="gds_menu"/>
  <Dataset id="gds_openPage">
    <ColumnInfo>
      <Column id="menuId" type="STRING" size="256"/>
      <Column id="menuName" type="STRING" size="256"/>
      <Column id="formId" type="STRING" size="256"/>
      <Column id="isPopup" type="STRING" size="256"/>
      <Column id="prgId" type="STRING" size="256"/>
      <Column id="svcGroup" type="STRING" size="256"/>
      <Column id="openTime" type="STRING" size="256"/>
    </ColumnInfo>
  </Dataset>
  <Dataset id="gds_message">
    <ColumnInfo>
      <Column id="ID" type="STRING" size="256"/>
      <Column id="TEXT" type="STRING" size="256"/>
    </ColumnInfo>
    <Rows>
      <Row>
        <Col id="ID">msg.session.timeout</Col>
        <Col id="TEXT">세션이 종료되었습니다. 다시 로그인해주세요.</Col>
      </Row>
      <Row>
        <Col id="ID">msg.error</Col>
        <Col id="TEXT">시스템 관리자에게 문의하세요.</Col>
      </Row>
      <Row>
        <Col id="ID">msg.login.url.error</Col>
        <Col id="TEXT">정상적인 경로로 접속하시기 바랍니다.</Col>
      </Row>
      <Row>
        <Col id="ID">msg.login.error</Col>
        <Col id="TEXT">해당하는 사용자 정보가 없습니다.</Col>
      </Row>
      <Row>
        <Col id="ID">msg.nomenu</Col>
        <Col id="TEXT">해당 Menu가 존재하지 않습니다.</Col>
      </Row>
      <Row>
        <Col id="ID">msg.maxopen</Col>
        <Col id="TEXT">업무화면은 $1 개를 초과 할 수 없습니다.</Col>
      </Row>
      <Row>
        <Col id="ID">msg.maxopen.po</Col>
        <Col id="TEXT">전사구매 업무화면은 $1 개를 초과 할 수 없습니다.</Col>
      </Row>
      <Row>
        <Col id="ID">msg.mem.lack</Col>
        <Col id="TEXT">PC 메모리가 부족하여 화면을 열 수 없습니다.@사용하지 않는 프로그램을 종료하고 사용하십시오.</Col>
      </Row>
      <Row>
        <Col id="ID">confirm.mem.lack.po</Col>
        <Col id="TEXT">PC 메모리가 부족하여 전사구매 화면을 열 수 없습니다.@사용하지 않는 프로그램을 종료하고 사용하십시오.@현 상태에서 전사구매 화면을 별도의 브라우저로 여시겠습니까?</Col>
      </Row>
      <Row>
        <Col id="ID">confirm.logout</Col>
        <Col id="TEXT">로그아웃 하시겠습니까?</Col>
      </Row>
      <Row>
        <Col id="ID">confirm.allclose</Col>
        <Col id="TEXT">모든 화면을 닫으시겠습니까?</Col>
      </Row>
      <Row>
        <Col id="ID">confirm.before.movepage</Col>
        <Col id="TEXT">변경된 데이터가 있습니다. 현재 화면을 닫겠습니까?</Col>
      </Row>
      <Row>
        <Col id="ID">confirm.before.search</Col>
        <Col id="TEXT">검색을 진행하면 변경된 데이터가 사라집니다.@계속 진행 하시겠습니까?</Col>
      </Row>
      <Row>
        <Col id="ID">confirm.before.moveropos</Col>
        <Col id="TEXT">해당 row의 위치를 이동하면 변경된 데이터가 사라집니다.@계속 진행 하시겠습니까?</Col>
      </Row>
      <Row>
        <Col id="ID">confirm.before.delete</Col>
        <Col id="TEXT">선택된 자료를 삭제 하시겠습니까?</Col>
      </Row>
      <Row>
        <Col id="ID">confirm.before.deletesave</Col>
        <Col id="TEXT">선택된 자료를 삭제 후 저장하시겠습니까?</Col>
      </Row>
      <Row>
        <Col id="ID">confirm.before.save</Col>
        <Col id="TEXT">자료를 저장 하시겠습니까?</Col>
      </Row>
      <Row>
        <Col id="ID">confirm.before.delete</Col>
        <Col id="TEXT">정말로 삭제 하시겠습니까?</Col>
      </Row>
      <Row>
        <Col id="ID">confirm.before.copy</Col>
        <Col id="TEXT">선택된 자료를 복사 하시겠습니까?</Col>
      </Row>
      <Row>
        <Col id="ID">confirm.before.action</Col>
        <Col id="TEXT">작업을 처리하시겠습니까?</Col>
      </Row>
      <Row>
        <Col id="ID">confirm.before.approve</Col>
        <Col id="TEXT">선택된 자료를 승인처리 하시겠습니까?</Col>
      </Row>
      <Row>
        <Col id="ID">confirm.before.approve.cancel</Col>
        <Col id="TEXT">선택된 자료를 승인취소처리 하시겠습니까?</Col>
      </Row>
      <Row>
        <Col id="ID">confirm.batch.execute</Col>
        <Col id="TEXT">배치 Job을 실행하시겠습니까?</Col>
      </Row>
      <Row>
        <Col id="ID">confirm.batch.stop</Col>
        <Col id="TEXT">배치 Job을 중지하시겠습니까?</Col>
      </Row>
      <Row>
        <Col id="ID">confirm.webdoc.attach</Col>
        <Col id="TEXT">작성한 웹문서를 첨부하시겠습니까?</Col>
      </Row>
      <Row>
        <Col id="ID">msg.pers.info.agree</Col>
        <Col id="TEXT">시스템 사용을 위해서는 개인정보취급방침에 동의하셔야 합니다.</Col>
      </Row>
      <Row>
        <Col id="ID">msg.pers.info.not.agree</Col>
        <Col id="TEXT">개인정보취급방침에 동의하지 않아 시스템을 사용할 수 없습니다.</Col>
      </Row>
      <Row>
        <Col id="ID">msg.pwd.must.change</Col>
        <Col id="TEXT">비밀번호 변경주기가 지났습니다. 비밀번호를 변경해야 시스템을 사용할 수 있습니다.</Col>
      </Row>
      <Row>
        <Col id="ID">msg.pwd.must.change.in.lock</Col>
        <Col id="TEXT">일정기간 동안 시스템을 사용하지 않아 계정이 잠긴 상태입니다. 비밀번호를 변경해야 시스템을 사용할 수 있습니다.</Col>
      </Row>
      <Row>
        <Col id="ID">msg.pwd.must.change.by.init</Col>
        <Col id="TEXT">관리자에 의해 비밀번호가 초기화 되었습니다. 비밀번호를 변경해야 시스템을 사용할 수 있습니다.</Col>
      </Row>
      <Row>
        <Col id="ID">msg.pers.must.change</Col>
        <Col id="TEXT">시스템에서 발송하는 중요 메시지를 전달받으려면 개인정보취급방침에서 동의한 필수 항목을 입력하셔야 합니다.</Col>
      </Row>
      <Row>
        <Col id="ID">msg.pers.no.input</Col>
        <Col id="TEXT">개인정보취급방침에서 동의한 필수 항목을 입력하시지 않았습니다. 초기화면에서 개인정보를 변경하실 수 있습니다.</Col>
      </Row>
      <Row>
        <Col id="ID">msg.pers.no.mask.not.export.excel</Col>
        <Col id="TEXT">마스크 처리되지 않은 개인정보가 있는 경우는 엑셀로 받을 수 없습니다.</Col>
      </Row>
      <Row>
        <Col id="ID">msg.pers.no.mask.not.report</Col>
        <Col id="TEXT">마스크 처리되지 않은 개인정보가 있는 경우는 인쇄할 수 없습니다.</Col>
      </Row>
      <Row>
        <Col id="ID">msg.pers.proc.grade.not.set</Col>
        <Col id="TEXT">개인정보처리등급 또는 권한정보가 설정되어 있지 않습니다. @관리자에게 연락하여 확인하십시오!@</Col>
      </Row>
      <Row>
        <Col id="ID">msg.batch.completed</Col>
        <Col id="TEXT">배치 Job이 종료되었습니다.</Col>
      </Row>
      <Row>
        <Col id="ID">msg.batch.running</Col>
        <Col id="TEXT">배치 Job이 실행 중입니다.</Col>
      </Row>
      <Row>
        <Col id="ID">msg.batch.multirunning</Col>
        <Col id="TEXT">여러 건의 배치 Job이 실행 중입니다. 실행 중인 배치 Job을 확인하십시오.</Col>
      </Row>
      <Row>
        <Col id="ID">msg.noselect</Col>
        <Col id="TEXT">$1 을(를) 선택해 주십시요.</Col>
      </Row>
      <Row>
        <Col id="ID">msg.noinput</Col>
        <Col id="TEXT">$1 을(를) 입력해 주십시요.</Col>
      </Row>
      <Row>
        <Col id="ID">msg.search.nodata</Col>
        <Col id="TEXT">조건에 해당하는 자료가 없습니다.</Col>
      </Row>
      <Row>
        <Col id="ID">msg.search.before</Col>
        <Col id="TEXT">먼저 데이터를 조회하여 주십시요.</Col>
      </Row>
      <Row>
        <Col id="ID">msg.save.nochange</Col>
        <Col id="TEXT">변경된 내역이 없습니다.</Col>
      </Row>
      <Row>
        <Col id="ID">msg.save.nodata</Col>
        <Col id="TEXT">저장할 데이터가 없습니다.</Col>
      </Row>
      <Row>
        <Col id="ID">msg.save.success</Col>
        <Col id="TEXT">저장 되었습니다.</Col>
      </Row>
      <Row>
        <Col id="ID">msg.save.sign.success</Col>
        <Col id="TEXT">전자결재 상신이 정상적으로 처리 되었습니다.</Col>
      </Row>
      <Row>
        <Col id="ID">msg.update.success</Col>
        <Col id="TEXT">수정 되었습니다.</Col>
      </Row>
      <Row>
        <Col id="ID">msg.delete.success</Col>
        <Col id="TEXT">삭제 되었습니다.</Col>
      </Row>
      <Row>
        <Col id="ID">msg.action.success</Col>
        <Col id="TEXT">처리 되었습니다.</Col>
      </Row>
      <Row>
        <Col id="ID">msg.batch.execute.success</Col>
        <Col id="TEXT">정상적으로 배치 Job이 실행 되었습니다.</Col>
      </Row>
      <Row>
        <Col id="ID">msg.batch.stop.success</Col>
        <Col id="TEXT">정상적으로 배치 Job이 중지 되었습니다.</Col>
      </Row>
      <Row>
        <Col id="ID">msg.no.result.message</Col>
        <Col id="TEXT">결과 메시지가 없습니다.</Col>
      </Row>
      <Row>
        <Col id="ID">msg.copy.success</Col>
        <Col id="TEXT">복사 되었습니다.</Col>
      </Row>
      <Row>
        <Col id="ID">msg.filesave.success</Col>
        <Col id="TEXT">$1 파일로 저장되었습니다.</Col>
      </Row>
      <Row>
        <Col id="ID">msg.err.exist.code</Col>
        <Col id="TEXT">입력하는 Code ($1)값이 이미 등록되어 있습니다.</Col>
      </Row>
      <Row>
        <Col id="ID">msg.err.updateafter</Col>
        <Col id="TEXT">변경된 내역을 저장 후 작업하세요.</Col>
      </Row>
      <Row>
        <Col id="ID">msg.err.delete.child</Col>
        <Col id="TEXT">하위 자료가 있어 삭제할 수 없습니다.</Col>
      </Row>
      <Row>
        <Col id="ID">msg.err.grid.nodata</Col>
        <Col id="TEXT">데이타가 없습니다.</Col>
      </Row>
      <Row>
        <Col id="ID">msg.err.grid.noselect</Col>
        <Col id="TEXT">선택된 항목이 없습니다.</Col>
      </Row>
      <Row>
        <Col id="ID">msg.err.validator.required</Col>
        <Col id="TEXT">$1 은(는) 필수 입력 항목입니다.</Col>
      </Row>
      <Row>
        <Col id="ID">msg.err.validator.length</Col>
        <Col id="TEXT">$1 의 입력값의 길이는 $2 이어야 합니다.</Col>
      </Row>
      <Row>
        <Col id="ID">msg.err.validator.maxlength</Col>
        <Col id="TEXT">$1 의 입력값의 길이는 $2 이하이어야 합니다.</Col>
      </Row>
      <Row>
        <Col id="ID">msg.err.validator.minlength</Col>
        <Col id="TEXT">$1 의 입력값의 길이는 $2 이상이어야 합니다.</Col>
      </Row>
      <Row>
        <Col id="ID">msg.err.validator.maxlengthB</Col>
        <Col id="TEXT">$1 의 입력값의 길이는 $2 이하이어야 합니다.</Col>
      </Row>
      <Row>
        <Col id="ID">msg.err.validator.minlengthB</Col>
        <Col id="TEXT">$1 의 입력값의 길이는 $2 이상이어야 합니다.</Col>
      </Row>
      <Row>
        <Col id="ID">msg.err.validator.digits</Col>
        <Col id="TEXT">$1 은(는) 숫자만 입력 가능합니다.</Col>
      </Row>
      <Row>
        <Col id="ID">msg.err.validator.min</Col>
        <Col id="TEXT">$1 은(는) $2 이상의 숫자만 입력 가능합니다.</Col>
      </Row>
      <Row>
        <Col id="ID">msg.err.validator.max</Col>
        <Col id="TEXT">$1 은(는) $2 이하의 숫자만 입력 가능합니다.</Col>
      </Row>
      <Row>
        <Col id="ID">msg.err.validator.date</Col>
        <Col id="TEXT">$1 은(는) 유효하지 않은 날짜 형식입니다.</Col>
      </Row>
      <Row>
        <Col id="ID">msg.err.validator.dateym</Col>
        <Col id="TEXT">$1 은(는) 유효하지 않은 년월 형식입니다.</Col>
      </Row>
      <Row>
        <Col id="ID">msg.err.validator.comparemax</Col>
        <Col id="TEXT">$1 이(가) $2 보다 작습니다.</Col>
      </Row>
      <Row>
        <Col id="ID">msg.err.validator.comparemin</Col>
        <Col id="TEXT">$1 이(가) $2 보다 큽니다.</Col>
      </Row>
      <Row>
        <Col id="ID">msg.err.validator.chknumber.n</Col>
        <Col id="TEXT">$1 은(는) 숫자만 입력 가능합니다.</Col>
      </Row>
      <Row>
        <Col id="ID">msg.err.validator.equalto</Col>
        <Col id="TEXT">$1 이(가) $2 와(과) 틀립니다.</Col>
      </Row>
      <Row>
        <Col id="ID">msg.err.validator.range</Col>
        <Col id="TEXT">$1 은(는) $2 와(과) $3 사이의 값입니다.</Col>
      </Row>
      <Row>
        <Col id="ID">msg.err.validator.declimit</Col>
        <Col id="TEXT">$1 은(는) 소숫점 $2 자리로 구성되어야 합니다.</Col>
      </Row>
      <Row>
        <Col id="ID">msg.err.validator.code</Col>
        <Col id="TEXT">$1 은(는) $2 의 값이어야 합니다.</Col>
      </Row>
      <Row>
        <Col id="ID">msg.err.validator.email</Col>
        <Col id="TEXT">e-mail이 잘못된 형태로 입력 되었습니다.</Col>
      </Row>
      <Row>
        <Col id="ID">msg.err.validator.url</Col>
        <Col id="TEXT">웹사이트 주소가 잘못 입력 되었습니다.</Col>
      </Row>
      <Row>
        <Col id="ID">msg.err.validator.phone</Col>
        <Col id="TEXT">전화번호가 잘못된 형태로 입력 되었습니다.</Col>
      </Row>
      <Row>
        <Col id="ID">msg.err.validator.zipcode</Col>
        <Col id="TEXT">우편번호가 잘못된 형태로 입력 되었습니다.</Col>
      </Row>
      <Row>
        <Col id="ID">msg.err.maxdate</Col>
        <Col id="TEXT">날짜의 입력 가능 범위를 벗어났습니다.</Col>
      </Row>
      <Row>
        <Col id="ID">msg.err.validator.date.great</Col>
        <Col id="TEXT">종료일이 시작일보다 빠릅니다.</Col>
      </Row>
      <Row>
        <Col id="ID">msg.err.filesize</Col>
        <Col id="TEXT">첨부 파일의 용량은 최고 $1 MB까지 입니다.</Col>
      </Row>
      <Row>
        <Col id="TEXT">경로가 지정되지 않았습니다.</Col>
        <Col id="ID">msg.err.nofilepath</Col>
      </Row>
      <Row>
        <Col id="ID">msg.err.filename</Col>
        <Col id="TEXT">파일 이름이 정의되지 않았습니다.</Col>
      </Row>
      <Row>
        <Col id="TEXT">첨부 파일은 $1개 이상 등록 할 수 없습니다.</Col>
        <Col id="ID">msg.err.filecount</Col>
      </Row>
      <Row>
        <Col id="ID">msg.err.uploadfail</Col>
        <Col id="TEXT">파일업로드가 실패하였습니다.</Col>
      </Row>
      <Row>
        <Col id="ID">msg.err.downloadfail</Col>
        <Col id="TEXT">파일 다운로드가 실패하였습니다.</Col>
      </Row>
      <Row>
        <Col id="ID">msg.err.filesavefail</Col>
        <Col id="TEXT">첨부파일 정보 저장에 실패하였습니다.</Col>
      </Row>
      <Row>
        <Col id="ID">msg.err.noExtentionFile</Col>
        <Col id="TEXT">첨부할 수 없는 형식의 파일입니다.($1)</Col>
      </Row>
      <Row>
        <Col id="ID">msg.err.dupfilename</Col>
        <Col id="TEXT">중복되는 파일명($1)이 있습니다.</Col>
      </Row>
      <Row>
        <Col id="ID">msg.err.filenamelength</Col>
        <Col id="TEXT">파일명 길이가 너무 깁니다. 파일명은 100Byte보다 작어야 합니다.</Col>
      </Row>
      <Row>
        <Col id="ID">msg.err.notselectfile</Col>
        <Col id="TEXT">선택된 파일이 없습니다.</Col>
      </Row>
      <Row>
        <Col id="ID">msg.file.fileDownloadComplete</Col>
        <Col id="TEXT">파일다운로드가 완료되었습니다.</Col>
      </Row>
      <Row>
        <Col id="ID">msg.file.needFileId</Col>
        <Col id="TEXT">첨부파일 참조일련번호가 필요합니다.</Col>
      </Row>
      <Row>
        <Col id="ID">msg.err.fileNotExistFile</Col>
        <Col id="TEXT">파일이 존재하지 않습니다.</Col>
      </Row>
      <Row>
        <Col id="ID">msg.err.filePomptExistFile</Col>
        <Col id="TEXT">해당 폴더에 파일이 존재합니다. 해당 파일을 덮어 쓰시겠습니까?</Col>
      </Row>
      <Row>
        <Col id="ID">msg.err.can.not.delete.sign</Col>
        <Col id="TEXT">전자결재 처리 건은 수정/삭제할 수 없습니다!</Col>
      </Row>
      <Row>
        <Col id="ID">ftp.confirm.before.copy</Col>
        <Col id="TEXT">품의복사 하시겠습니까?</Col>
      </Row>
      <Row>
        <Col id="ID">ftp.err.validator.draft</Col>
        <Col id="TEXT">상신중이거나 승인완료 상태는 삭제할 수 없습니다.</Col>
      </Row>
      <Row>
        <Col id="ID">ftp.err.validator.proposal.save</Col>
        <Col id="TEXT">품의번호[ $1 ]에 대하여 저장 하시겠습니까?</Col>
      </Row>
      <Row>
        <Col id="ID">ftp.err.validator.poorder.delete</Col>
        <Col id="TEXT">구매주문상태가 확정 상태는 삭제할 수 없습니다.</Col>
      </Row>
      <Row>
        <Col id="TEXT">P/O No[ $1 ] 에 대하여 확정 하시겠습니까?</Col>
        <Col id="ID">ftp.confirm.validator.poorder.confirm</Col>
      </Row>
      <Row>
        <Col id="ID">ftp.err.validator.poorder.confirm</Col>
        <Col id="TEXT">품의 승인상태에서 확정 가능합니다.</Col>
      </Row>
      <Row>
        <Col id="ID">ftp.err.validator.poorder.confirm2</Col>
        <Col id="TEXT">확정상태입니다 취소 후 확정 가능합니다.</Col>
      </Row>
      <Row>
        <Col id="ID">ftp.err.validator.poorder.cancel</Col>
        <Col id="TEXT">구매주문 확정상태에서 취소 가능합니다.</Col>
      </Row>
      <Row>
        <Col id="TEXT">P/O No[ $1]에 대하여 확정 취소 하시겠습니까?</Col>
        <Col id="ID">ftp.confirm.validator.poorder.cancel</Col>
      </Row>
      <Row>
        <Col id="ID">ftp.validator.tabmove</Col>
        <Col id="TEXT">저장 후 기타선급금 정산 탭으로 이동 가능합니다.</Col>
      </Row>
      <Row>
        <Col id="ID">ftp.validator.nodeal</Col>
        <Col id="TEXT">자전거래(매출처와 매입처가 같은)는 할 수 없습니다.</Col>
      </Row>
      <Row>
        <Col id="TEXT">정산 잔액이 없습니다.</Col>
        <Col id="ID">ftp.validator.no.adjust.valamt</Col>
      </Row>
      <Row>
        <Col id="TEXT">기타선급금 총액[ $1]보다 정산잔액[ $2]이 큽니다.</Col>
        <Col id="ID">ftp.validator.adjust.valamt.chk</Col>
      </Row>
      <Row>
        <Col id="ID">ft.gds.confirm.before.if</Col>
        <Col id="TEXT">$1 전표 I/F하시겠습니까?</Col>
      </Row>
      <Row>
        <Col id="ID">ft.gds.confirm.before.ifcancel</Col>
        <Col id="TEXT">$1 전표 I/F 취소  하시겠습니까?</Col>
      </Row>
      <Row>
        <Col id="ID">ftp.err.validator.poorder.confirm</Col>
        <Col id="TEXT">품의 승인상태에서 확정 가능합니다.</Col>
      </Row>
      <Row>
        <Col id="TEXT">P/O No[ $1]에 대하여 확정 취소 하시겠습니까?</Col>
        <Col id="ID">ftp.confirm.validator.poorder.cancel</Col>
      </Row>
      <Row>
        <Col id="ID">ftp.err.validator.poorder.cancel</Col>
        <Col id="TEXT">구매주문 확정상태에서 취소 가능합니다.</Col>
      </Row>
      <Row>
        <Col id="ID">ftp.err.validator.poorder.confirm2</Col>
        <Col id="TEXT">확정상태입니다 취소 후 확정 가능합니다.</Col>
      </Row>
      <Row>
        <Col id="ID">ftp.validator.no.same</Col>
        <Col id="TEXT">품목의 매입액 합계 [ $1 ] 와 지불조건의 지불예정금 합계[ $2 ] 은 같아야 합니다.</Col>
      </Row>
      <Row>
        <Col id="TEXT">전표가 등록되어 있습니다. 삭제 후 진행하세요.</Col>
        <Col id="ID">ft.gds.alert.slip.reg</Col>
      </Row>
      <Row>
        <Col id="ID">ft.gds.alert.slip.reg2</Col>
        <Col id="TEXT">전표가 생성되어 있습니다. 전표 I/F취소후 진행하세요.</Col>
      </Row>
      <Row>
        <Col id="TEXT">삭제할 물품 대금이 없습니다.</Col>
        <Col id="ID">ft.gds.alert.delete.no.gdspaym</Col>
      </Row>
      <Row>
        <Col id="ID">ft.fdm.alert.no.pono</Col>
        <Col id="TEXT">서로 다른 PO No와 세팅 될 수 없습니다.</Col>
      </Row>
      <Row>
        <Col id="TEXT">통관완료수량과 통관수량의 합이 PO수량보다 클 수 없습니다.</Col>
        <Col id="ID">ft.fdm.alert.no.sum</Col>
      </Row>
      <Row>
        <Col id="ID">ft.fdm.validator.deliver</Col>
        <Col id="TEXT">수입문서번호 [$1]는 이미 입고되었습니다. 입고 취소 후 가능합니다.</Col>
      </Row>
      <Row>
        <Col id="ID">ft.fdm.validator.deliver.cancel</Col>
        <Col id="TEXT">수입문서번호  [$1]는 입고된 내역이 없습니다. 입고 후 취소 가능합니다.</Col>
      </Row>
      <Row>
        <Col id="ID">ft.fdm.confirm.deliver</Col>
        <Col id="TEXT">$1 처리하시겠습니까?</Col>
      </Row>
      <Row>
        <Col id="ID">sc.no.copydata</Col>
        <Col id="TEXT">복사할 자료가 없습니다.</Col>
      </Row>
      <Row>
        <Col id="ID">sc.confirm.copydata</Col>
        <Col id="TEXT">복사한 자료를 붙여넣기 하겠습니까?</Col>
      </Row>
      <Row>
        <Col id="ID">sc.no.pastedata</Col>
        <Col id="TEXT">붙여넣기할 자료가 없습니다.</Col>
      </Row>
      <Row>
        <Col id="ID">sc.sca.authbymenumgmt.error01</Col>
        <Col id="TEXT">해당 메뉴는 이미 등록된 메뉴입니다.@@행번호 : $1@메뉴ID : $2@메뉴명 : $3</Col>
      </Row>
      <Row>
        <Col id="ID">sc.add.choice.data</Col>
        <Col id="TEXT">선택된 자료를 추가 하시겠습니까?</Col>
      </Row>
      <Row>
        <Col id="ID">sc.no.choice.data</Col>
        <Col id="TEXT">선택된 자료가 없습니다.</Col>
      </Row>
      <Row>
        <Col id="ID">msg.err.validator.data</Col>
        <Col id="TEXT">$1 이(가) 잘못된 형태로 입력 되었습니다.</Col>
      </Row>
      <Row>
        <Col id="ID">msg.err.duplicatedata</Col>
        <Col id="TEXT">입력하신 $1 은(는) 이미 등록된 자료입니다.</Col>
      </Row>
      <Row>
        <Col id="ID">msg.err.validator.time.great</Col>
        <Col id="TEXT">종료시간이 시작시간보다 빠릅니다.</Col>
      </Row>
      <Row>
        <Col id="ID">sc.sca.authmappingmgmt.error01</Col>
        <Col id="TEXT">이미 등록되어 있는 CC입니다.@@행번호 : $1@CC코드 : $2@CC명 : $3</Col>
      </Row>
      <Row>
        <Col id="ID">sc.sca.authmappingmgmt.error02</Col>
        <Col id="TEXT">이미 등록되어 있는 Role입니다.@@Role : $1@Role명 : $2</Col>
      </Row>
      <Row>
        <Col id="ID">sc.sca.authmappingmgmt.error03</Col>
        <Col id="TEXT">이미 등록되어 있는 사용자군입니다.@@행번호 : $1@사용자군코드 : $2@사용자군명 : $3</Col>
      </Row>
      <Row>
        <Col id="ID">msg.err.overlap.date</Col>
        <Col id="TEXT">$1 이(가) 중복 입력되었습니다.</Col>
      </Row>
      <Row>
        <Col id="ID">msg.err.maxdata.date</Col>
        <Col id="TEXT">$1 을(를) 초과하였습니다</Col>
      </Row>
      <Row>
        <Col id="ID">msg.err.mindata.date</Col>
        <Col id="TEXT">$1 을(를) 미만입니다.</Col>
      </Row>
      <Row>
        <Col id="ID">sc.scu.userrole.add.no.data</Col>
        <Col id="TEXT">사용자 권한을 적용하고자 하는 사용자가 조회되지 않았습니다.</Col>
      </Row>
      <Row>
        <Col id="ID">sc.scu.no.user.data</Col>
        <Col id="TEXT">조회된 사용자가 없습니다.</Col>
      </Row>
      <Row>
        <Col id="ID">sc.scu.usermngt.001</Col>
        <Col id="TEXT">같은 사용자에게는 붙여넣기를 할 수가 없습니다.</Col>
      </Row>
      <Row>
        <Col id="ID">sc.scu.usermngt.002</Col>
        <Col id="TEXT">시스템구분이 일치하지 않습니다.@@시스템구분 : $1을(를) 선택하여 주세요.</Col>
      </Row>
      <Row>
        <Col id="ID">sc.scu.useridreq.001</Col>
        <Col id="TEXT">입력하신 아이디($1)는 사용할 수 없습니다.</Col>
      </Row>
      <Row>
        <Col id="ID">sc.scu.useridreq.002</Col>
        <Col id="TEXT">사용 가능한 아이디입니다.</Col>
      </Row>
      <Row>
        <Col id="ID">sc.scu.useridreq.003</Col>
        <Col id="TEXT">아이디(중복체크)를 확인해 주세요.</Col>
      </Row>
      <Row>
        <Col id="ID">sc.scu.useridreq.004</Col>
        <Col id="TEXT">[$1] 요청을 하시겠습니까?</Col>
      </Row>
      <Row>
        <Col id="ID">sc.scu.useridreq.005</Col>
        <Col id="TEXT">[$1] 요청을 하였습니다.</Col>
      </Row>
      <Row>
        <Col id="ID">sc.scu.useridreq.006</Col>
        <Col id="TEXT">요청하신 내용을 승인처리 하였습니다.</Col>
      </Row>
      <Row>
        <Col id="ID">sc.scu.useridreq.007</Col>
        <Col id="TEXT">승인처리시 오류가 발생하였습니다.</Col>
      </Row>
      <Row>
        <Col id="ID">sc.scu.useridreq.008</Col>
        <Col id="TEXT">승인처리를 수행하시겠습니까?</Col>
      </Row>
      <Row>
        <Col id="ID">sc.scu.useridreq.009</Col>
        <Col id="TEXT">중단처리를 수행하시겠습니까?</Col>
      </Row>
      <Row>
        <Col id="ID">rc.sle.no.input.data</Col>
        <Col id="TEXT">전체가 입력 되어 더이상 입력할 수 없습니다.</Col>
      </Row>
      <Row>
        <Col id="ID">rc.sle.save.data</Col>
        <Col id="TEXT">처리된 결과를 저장하시겠습니까?</Col>
      </Row>
      <Row>
        <Col id="ID">rc.sle.resave.data</Col>
        <Col id="TEXT">변경된 자료는 나중에 저장하시기 바랍니다.</Col>
      </Row>
      <Row>
        <Col id="ID">rc.sle.no.data</Col>
        <Col id="TEXT">입력할 수 없는 자료 입니다.</Col>
      </Row>
      <Row>
        <Col id="ID">sc.scz.cust.msg001</Col>
        <Col id="TEXT">이미 등록된 거래처입니다.@해당 거래처의 정보를 바탕으로 신규 거래처로 생성하시겠습니까?</Col>
      </Row>
      <Row>
        <Col id="ID">sc.scz.cust.msg002</Col>
        <Col id="TEXT">SAP에만 등록된 거래처입니다.@SAP의 거래처 정보를 바탕으로 신규 거래처로 생성하시겠습니까?</Col>
      </Row>
      <Row>
        <Col id="ID">sc.cmn.cert.fail.exceed.time</Col>
        <Col id="TEXT">인증 시간이 초과되어 인증에 실패하였습니다.</Col>
      </Row>
      <Row>
        <Col id="ID">rc.sle.not.previous</Col>
        <Col id="TEXT">[$1] 처음 자료 입니다.</Col>
      </Row>
      <Row>
        <Col id="ID">rc.sle.not.next</Col>
        <Col id="TEXT">[$1] 마지막 자료 입니다.</Col>
      </Row>
      <Row>
        <Col id="ID">rc.bms.eventCopy</Col>
        <Col id="TEXT">예약번호 [$1] 를(을) 신규로 복사 하시겠습니까?</Col>
      </Row>
      <Row>
        <Col id="ID">sc.scz.cust.request.msg001</Col>
        <Col id="TEXT">이미 등록되어 있는 거래처입니다.@신규 거래처로 등록하시겠습니까?</Col>
      </Row>
      <Row>
        <Col id="ID">sc.scz.cust.request.msg002</Col>
        <Col id="TEXT">SAP에만 등록되어있는 거래처입니다.@거래처로 사용하기 위해서는 반드시 [저장]하셔야 합니다.@@지금 SAP의 정보를 가져옵니다.</Col>
      </Row>
      <Row>
        <Col id="ID">sc.scz.cust.request.msg003</Col>
        <Col id="TEXT">현재 신청중인 거래처입니다.@@- 신청일자 : $1@- 신 청 자 : $2@- 신청사번 : $3@@신규 거래처로 등록하시겠습니까?</Col>
      </Row>
      <Row>
        <Col id="ID">sc.scz.cust.request.msg004</Col>
        <Col id="TEXT">$1건의 거래처가 등록되어 있습니다.@상위거래처의 정보를 바탕으로 생성하시겠습니까?</Col>
      </Row>
      <Row>
        <Col id="ID">sc.scz.cust.request.msg005</Col>
        <Col id="TEXT">$1건의 거래처가 신청중입니다.@상위거래처의 정보를 바탕으로 생성하시겠습니까?</Col>
      </Row>
      <Row>
        <Col id="ID">sc.scz.cust.request.msg006</Col>
        <Col id="TEXT">탭을 변경하시면 변경된 데이터가 사라집니다.@그래도 탭을 변경하시겠습니까?</Col>
      </Row>
      <Row>
        <Col id="ID">sc.scz.cust.request.msg007</Col>
        <Col id="TEXT">이미 등록되거나 신청중인 고객은 추가 신청을 하실 수가 없습니다.</Col>
      </Row>
      <Row>
        <Col id="ID">sc.scz.cust.request.msg008</Col>
        <Col id="TEXT">SAP에만 등록되어있는 고객입니다.@고객으로 사용하기 위해서는 반드시 [저장]하셔야 합니다.@@지금 SAP의 정보를 가져옵니다.</Col>
      </Row>
      <Row>
        <Col id="ID">sc.scz.cust.request.msg009</Col>
        <Col id="TEXT">이미 등록되거나 신청중인 해외거래처는 추가 신청을 하실 수가 없습니다.</Col>
      </Row>
      <Row>
        <Col id="ID">sc.scz.cust.request.msg010</Col>
        <Col id="TEXT">SAP에만 등록되어있는 해외거래처입니다.@해외거래처로 사용하기 위해서는 반드시 [저장]하셔야 합니다.@@지금 SAP의 정보를 가져옵니다.</Col>
      </Row>
      <Row>
        <Col id="ID">msg.action.close.success</Col>
        <Col id="TEXT">정상적으로 마감처리 되었습니다.</Col>
      </Row>
      <Row>
        <Col id="ID">msg.action.close.cancel</Col>
        <Col id="TEXT">정상적으로 마감취소 되었습니다..</Col>
      </Row>
      <Row>
        <Col id="ID">msg.msgsend.success</Col>
        <Col id="TEXT">$1 건의 메시지가 전송되었습니다.</Col>
      </Row>
      <Row>
        <Col id="ID">msg.msgsend.no.receiver</Col>
        <Col id="TEXT">메시지 수신자가 없습니다.</Col>
      </Row>
      <Row>
        <Col id="ID">rc.bms.err.updateAfter</Col>
        <Col id="TEXT">입력중 입니다. @입력중인 데이터가 사라집니다. @진행 하시겠습니까?</Col>
      </Row>
      <Row>
        <Col id="ID">rc.bms.err.addAfter</Col>
        <Col id="TEXT">기본 정보 입력후 등록이 가능 합니다.</Col>
      </Row>
      <Row>
        <Col id="ID">rc.bms.end.updateAfter</Col>
        <Col id="TEXT">자료를 저장 하시겠습니까? @@$1 의 행사 상태가 [종료] 상태로 변경 됩니다.@진행 하시겠습니까?</Col>
      </Row>
      <Row>
        <Col id="ID">rc.bms.end.endContents</Col>
        <Col id="TEXT">완료 보고서 내역을 입력 하십시오!</Col>
      </Row>
      <Row>
        <Col id="ID">rc.bms.err.saveAfter</Col>
        <Col id="TEXT">연회룸 자료가 없습니다. @연회룸 최소 1건은 존재 해야 저장 가능 합니다.</Col>
      </Row>
    </Rows>
  </Dataset>
  <Dataset id="gds_gridMenu">
    <ColumnInfo>
      <Column id="menuLvl" type="STRING" size="256"/>
      <Column id="menuId" type="STRING" size="256"/>
      <Column id="menuNm" type="STRING" size="256"/>
      <Column id="bUse" type="STRING" size="256"/>
      <Column id="bEnbleColumn" type="STRING" size="256"/>
      <Column id="hotKey" type="STRING" size="256"/>
    </ColumnInfo>
    <Rows>
      <Row>
        <Col id="menuLvl">0</Col>
        <Col id="menuId">200</Col>
        <Col id="menuNm">인쇄</Col>
        <Col id="bUse">Y</Col>
        <Col id="bEnbleColumn">1</Col>
        <Col id="hotKey">Ctrl+P</Col>
      </Row>
      <Row>
        <Col id="menuLvl">0</Col>
        <Col id="menuId">210</Col>
        <Col id="menuNm">다중정렬</Col>
        <Col id="bUse">Y</Col>
        <Col id="bEnbleColumn">1</Col>
        <Col id="hotKey">Ctrl+M</Col>
      </Row>
      <Row>
        <Col id="menuLvl">0</Col>
        <Col id="menuId">220</Col>
        <Col id="menuNm">다중필터</Col>
        <Col id="bUse">Y</Col>
        <Col id="bEnbleColumn">1</Col>
        <Col id="hotKey">Ctrl+T</Col>
      </Row>
      <Row>
        <Col id="menuLvl">0</Col>
        <Col id="menuId">230</Col>
        <Col id="menuNm">검색</Col>
        <Col id="bUse">Y</Col>
        <Col id="bEnbleColumn">1</Col>
        <Col id="hotKey">Ctrl+F</Col>
      </Row>
      <Row>
        <Col id="menuNm">-</Col>
        <Col id="menuLvl">0</Col>
      </Row>
      <Row>
        <Col id="menuLvl">0</Col>
        <Col id="menuId">300</Col>
        <Col id="menuNm">정렬제거(전체)</Col>
        <Col id="bUse">Y</Col>
        <Col id="bEnbleColumn">1</Col>
      </Row>
      <Row>
        <Col id="menuLvl">0</Col>
        <Col id="menuId">310</Col>
        <Col id="menuNm">필터제거(전체)</Col>
        <Col id="bUse">Y</Col>
        <Col id="bEnbleColumn">1</Col>
      </Row>
      <Row>
        <Col id="menuLvl">0</Col>
        <Col id="menuId">[Undefined]</Col>
        <Col id="menuNm">-</Col>
        <Col id="bUse">[Undefined]</Col>
        <Col id="bEnbleColumn">[Undefined]</Col>
        <Col id="hotKey">[Undefined]</Col>
      </Row>
      <Row>
        <Col id="menuLvl">0</Col>
        <Col id="menuId">400</Col>
        <Col id="menuNm">Excel 내보내기(저장)</Col>
        <Col id="bUse">Y</Col>
        <Col id="bEnbleColumn">1</Col>
      </Row>
      <Row>
        <Col id="menuLvl">0</Col>
        <Col id="menuId">410</Col>
        <Col id="menuNm">Excel 내보내기</Col>
        <Col id="bUse">Y</Col>
        <Col id="bEnbleColumn">1</Col>
        <Col id="hotKey">Ctrl+E</Col>
      </Row>
      <Row>
        <Col id="menuLvl">0</Col>
        <Col id="menuId">[Undefined]</Col>
        <Col id="menuNm">-</Col>
        <Col id="bUse">[Undefined]</Col>
        <Col id="bEnbleColumn">[Undefined]</Col>
        <Col id="hotKey">[Undefined]</Col>
      </Row>
      <Row>
        <Col id="menuLvl">0</Col>
        <Col id="menuId">900</Col>
        <Col id="menuNm">칼럼숨기기</Col>
        <Col id="bUse">Y</Col>
        <Col id="bEnbleColumn">1</Col>
      </Row>
      <Row>
        <Col id="menuLvl">0</Col>
        <Col id="menuId">910</Col>
        <Col id="menuNm">컬럼보이기(전체)</Col>
        <Col id="bUse">Y</Col>
        <Col id="bEnbleColumn">1</Col>
      </Row>
      <Row>
        <Col id="menuLvl">0</Col>
        <Col id="menuNm">-</Col>
      </Row>
      <Row>
        <Col id="menuLvl">0</Col>
        <Col id="menuId">991</Col>
        <Col id="menuNm">라인복사</Col>
        <Col id="bUse">Y</Col>
        <Col id="bEnbleColumn">1</Col>
      </Row>
    </Rows>
  </Dataset>
  <Dataset id="gds_component">
    <ColumnInfo>
      <Column id="COMP_ID" type="STRING" size="256"/>
      <Column id="COMP_TYPE" type="STRING" size="256"/>
      <Column id="COMP_COMPOSITE" type="STRING" size="256"/>
      <Column id="COMP_OWNER" type="STRING" size="256"/>
      <Column id="COMP_USERDATA" type="STRING" size="256"/>
    </ColumnInfo>
  </Dataset>
  <Dataset id="gds_common_code">
    <ColumnInfo>
      <Column id="CD" type="STRING" size="256"/>
      <Column id="CODE_NAME" type="STRING" size="256"/>
    </ColumnInfo>
  </Dataset>
  <Dataset id="gds_Cwin"/>
  <Dataset id="gds_Csqlout"/>
  <Dataset id="gds_currdate"/>
  <Dataset id="gds_sql_common">
    <ColumnInfo>
      <Column id="sql" type="STRING" size="256"/>
      <Column id="code" type="STRING" size="256"/>
      <Column id="name" type="STRING" size="256"/>
      <Column id="code_dsp" type="STRING" size="256"/>
      <Column id="name_dsp" type="STRING" size="256"/>
      <Column id="ret_code" type="STRING" size="256"/>
      <Column id="ret_name" type="STRING" size="256"/>
      <Column id="val_code" type="STRING" size="256"/>
      <Column id="val_name" type="STRING" size="256"/>
      <Column id="add_where" type="STRING" size="256"/>
      <Column id="caption" type="STRING" size="256"/>
      <Column id="allfield" type="STRING" size="256"/>
      <Column id="in_orderby" type="STRING" size="256"/>
    </ColumnInfo>
  </Dataset>
  <Variable id="g_CtiUseYn"/>
  <Variable id="g_CtiUserId"/>
  <Variable id="g_PersInfoAgreeYn" initval="Y"/>
  <Variable id="g_PersInfoMask" initval="YYYYYYYYYYYYYY"/>
  <Variable id="g_PersInfoProcLevel" initval="99"/>
  <Variable id="gv_AuthLevels" initval="14,16,999"/>
  <Variable id="gv_webImgRoot" initval="http://localhost:8080/upload"/>
  <Variable id="gv_altNum"/>
  <Variable id="g_UserType"/>
  <Variable id="g_System_Mst"/>
  <Variable id="g_TempSabunManageSabun"/>
  <Dataset id="gds_limsAuthLevels" useclientlayout="true">
    <ColumnInfo>
      <Column id="authCd" type="STRING" size="256"/>
      <Column id="sabun" type="STRING" size="256"/>
      <Column id="insptFld" type="STRING" size="256"/>
    </ColumnInfo>
  </Dataset>
  <Variable id="g_IntroPage"/>
  <Dataset id="gds_SmSearch">
    <ColumnInfo>
      <Column id="empNum" type="STRING" size="256"/>
      <Column id="muCd" type="STRING" size="256"/>
      <Column id="muNm" type="STRING" size="256"/>
      <Column id="tmCd" type="STRING" size="256"/>
      <Column id="tmNm" type="STRING" size="256"/>
      <Column id="ccCd" type="STRING" size="256"/>
      <Column id="ccNm" type="STRING" size="256"/>
      <Column id="upjang" type="STRING" size="256"/>
      <Column id="upjangnm" type="STRING" size="256"/>
      <Column id="inputVal" type="STRING" size="256"/>
    </ColumnInfo>
  </Dataset>
  <Variable id="gv_MainUpjangImg"/>
  <Variable id="gv_upjang"/>
  <Variable id="gv_upjangnm"/>
  <Variable id="gv_mainUpjang"/>
  <Variable id="gv_mainUpjangNm"/>
  <Variable id="gv_manageAllowIp"/>
  <Variable id="gv_userRoles" initval="ADMIN,user01"/>
  <Variable id="gv_applyAuthYn" initval="N"/>
  <Variable id="gv_drawButtonYn" initval="N"/>
  <Variable id="gv_PtCd"/>
  <Variable id="gv_PtNm"/>
  <Variable id="gv_slipSabun"/>
  <Variable id="gv_UserChngSrcSabun"/>
  <Variable id="gv_ReturnDate"/>
  <Dataset id="gds_sql_common_2">
    <ColumnInfo>
      <Column id="sql" type="STRING" size="256"/>
      <Column id="code" type="STRING" size="256"/>
      <Column id="name" type="STRING" size="256"/>
      <Column id="code_dsp" type="STRING" size="256"/>
      <Column id="name_dsp" type="STRING" size="256"/>
      <Column id="ret_code" type="STRING" size="256"/>
      <Column id="ret_name" type="STRING" size="256"/>
      <Column id="ret_tmcd" type="STRING" size="256"/>
      <Column id="val_code" type="STRING" size="256"/>
      <Column id="val_name" type="STRING" size="256"/>
      <Column id="add_where" type="STRING" size="256"/>
      <Column id="caption" type="STRING" size="256"/>
      <Column id="allfield" type="STRING" size="256"/>
      <Column id="in_orderby" type="STRING" size="256"/>
    </ColumnInfo>
  </Dataset>
</GlobalVariables>
